damensm_profiling/__init__.py
damensm_profiling/damen_profiling.py
damen_profiling-0.1.5.dist-info/METADATA
damen_profiling-0.1.5.dist-info/WHEEL
damen_profiling-0.1.5.dist-info/top_level.txt
damen_profiling-0.1.5.dist-info/RECORD
