Metadata-Version: 2.4
Name: damen_profiling
Version: 0.1.5
Summary: Damen-library
Author-email: giandaeky <giandaekyoga10@gmail.com>
Requires-Python: >=3.8
